pulumi_spotinst/__init__.py
pulumi_spotinst/_inputs.py
pulumi_spotinst/_utilities.py
pulumi_spotinst/account.py
pulumi_spotinst/credentials_azure.py
pulumi_spotinst/credentials_gcp.py
pulumi_spotinst/data_integration.py
pulumi_spotinst/elastigroup_azure_v3.py
pulumi_spotinst/health_check.py
pulumi_spotinst/notification_center.py
pulumi_spotinst/ocean_right_sizing_rule.py
pulumi_spotinst/outputs.py
pulumi_spotinst/provider.py
pulumi_spotinst/pulumi-plugin.json
pulumi_spotinst/py.typed
pulumi_spotinst/stateful_node_azure.py
pulumi_spotinst/subscription.py
pulumi_spotinst/aws/__init__.py
pulumi_spotinst/aws/_inputs.py
pulumi_spotinst/aws/account.py
pulumi_spotinst/aws/beanstalk.py
pulumi_spotinst/aws/credentials.py
pulumi_spotinst/aws/elastigroup.py
pulumi_spotinst/aws/managed_instance.py
pulumi_spotinst/aws/mr_scalar.py
pulumi_spotinst/aws/ocean.py
pulumi_spotinst/aws/ocean_extended_resource_definition.py
pulumi_spotinst/aws/ocean_launch_spec.py
pulumi_spotinst/aws/outputs.py
pulumi_spotinst/aws/suspension.py
pulumi_spotinst/azure/__init__.py
pulumi_spotinst/azure/_inputs.py
pulumi_spotinst/azure/ocean_np.py
pulumi_spotinst/azure/ocean_np_virtual_node_group.py
pulumi_spotinst/azure/outputs.py
pulumi_spotinst/config/__init__.py
pulumi_spotinst/config/__init__.pyi
pulumi_spotinst/config/vars.py
pulumi_spotinst/ecs/__init__.py
pulumi_spotinst/ecs/_inputs.py
pulumi_spotinst/ecs/ocean.py
pulumi_spotinst/ecs/ocean_launch_spec.py
pulumi_spotinst/ecs/outputs.py
pulumi_spotinst/gcp/__init__.py
pulumi_spotinst/gcp/_inputs.py
pulumi_spotinst/gcp/elastigroup.py
pulumi_spotinst/gcp/outputs.py
pulumi_spotinst/gke/__init__.py
pulumi_spotinst/gke/_inputs.py
pulumi_spotinst/gke/elastigroup.py
pulumi_spotinst/gke/ocean_import.py
pulumi_spotinst/gke/ocean_launch_spec.py
pulumi_spotinst/gke/ocean_launch_spec_import.py
pulumi_spotinst/gke/outputs.py
pulumi_spotinst/oceancd/__init__.py
pulumi_spotinst/oceancd/_inputs.py
pulumi_spotinst/oceancd/outputs.py
pulumi_spotinst-3.128.3.dist-info/METADATA
pulumi_spotinst-3.128.3.dist-info/WHEEL
pulumi_spotinst-3.128.3.dist-info/top_level.txt
pulumi_spotinst-3.128.3.dist-info/RECORD
